{
  "Action": [
    {
      "id": 1,
      "question": "ทีมต้องข้ามหุบเขาอันตราย คุณจะทำอะไร?",
      "answers": [
        {
          "text": "กระตุ้นให้ทีมกล้าเสี่ยงและนำทางข้ามไปก่อน ",
          "value": "The Dynamo"
        },
        {
          "text": "ลงมือสร้างสะพานเชือกข้ามหุบเขาทันที ",
          "value": "The Doer"
        },
        {
          "text": "ตรวจสอบเส้นทางและอุปกรณ์ทุกชิ้นอย่างละเอียดก่อนออกเดินทาง",
          "value": "The Perfectionist"
        }
      ]
    },
    {
      "id": 2,
      "question": "ทีมเจอกับสัตว์ประหลาดยักษ์ คุณจะจัดการยังไง?",
      "answers": [
        {
          "text": "ตะโกนท้าทายสัตว์ประหลาดและนำทีมเข้าต่อสู้",
          "value": "The Dynamo"
        },
        {
          "text": "รีบหาอาวุธและสิ่งของรอบตัวมาประดิษฐ์กับดัก",
          "value": "The Doer"
        },
        {
          "text": "สังเกตพฤติกรรมของสัตว์อย่างละเอียดเพื่อหาจุดอ่อน",
          "value": "The Perfectionist"
        }
      ]
    },
    {
      "id": 3,
      "question": "ทีมต้องข้ามแม่น้ำที่เชี่ยวกราก คุณจะทำอะไร?",
      "answers": [
        {
          "text": "ให้ทีมแยกสำรวจเส้นทาง แล้วนำทีมข้ามแม่น้ำทันที",
          "value": "The Dynamo"
        },
        {
          "text": "ลงมือสร้างแพจากวัสดุรอบๆ ตัวทันที",
          "value": "The Doer"
        },
        {
          "text": "ตรวจสอบอุปกรณ์ทุกชิ้นให้แน่ใจว่าพร้อมสำหรับการข้ามแม่น้ำ",
          "value": "The Perfectionist"
        }
      ]
    },
    {
      "id": 4,
      "question": "ทีมต้องสร้างที่พักชั่วคราวในป่าทึบ คุณจะทำอย่างไร?",
      "answers": [
        {
          "text": "รีบลงมือสร้างที่พักอย่างรวดเร็วโดยใช้วัสดุที่หาได้รอบๆ ตัว",
          "value": "The Dynamo"
        },
        {
          "text": "วางแผนและแบ่งงานให้ทุกคนในทีมช่วยกันสร้างอย่างเป็นระบบ",
          "value": "The Doer"
        },
        {
          "text": "ออกแบบที่พักอย่างละเอียดโดยคำนึงถึงความปลอดภัยและความสะดวกสบาย ",
          "value": "The Perfectionist"
        }
      ]
    }
  ],
  "People": [
    {
      "id": 1,
      "question": "ทีมต้องเจรจากับเผ่าพื้นเมืองเพื่อขอความช่วยเหลือ คุณจะทำอย่างไร?",
      "answers": [
        {
          "text": "วางแผนการเจรจาและมอบหมายบทบาทให้แต่ละคนในทีม",
          "value": "The Maestro"
        },
        {
          "text": "พยายามสร้างบรรยากาศที่เป็นมิตรและเข้าใจวัฒนธรรมของพวกเขา",
          "value": "The Harmonizer"
        },
        {
          "text": "ใช้เครือข่ายความสัมพันธ์ที่มีเพื่อหาคนกลางในการเจรจา",
          "value": "The Networker"
        }
      ]
    },
    {
      "id": 2,
      "question": "ทีมเกิดความขัดแย้งเรื่องเส้นทางการเดินทาง คุณจะทำยังไง?",
      "answers": [
        {
          "text": "จัดประชุมและช่วยให้ทุกคนหาจุดร่วมกัน",
          "value": "The Maestro"
        },
        {
          "text": "พยายามประนีประนอมและหาทางออกที่ทุกคนพอใจ",
          "value": "The Harmonizer"
        },
        {
          "text": "กลับไปถามชนเผ่าพื้นเมืองที่ผ่านมา เพื่อถามว่าต้องไปทางไหน",
          "value": "The Networker"
        }
      ]
    },
    {
      "id": 3,
      "question": "ทีมต้องเลือกผู้นำในการบุกฝ่าป่าอันตราย คุณจะจัดการอย่างไร?",
      "answers": [
        {
          "text": "จัดการแข่งขันทักษะการเอาตัวรอดเพื่อหาผู้นำที่เหมาะสมที่สุด",
          "value": "The Maestro"
        },
        {
          "text": "พูดคุยกับทุกคนเพื่อหาอาสาสมัครที่มั่นใจและได้รับการยอมรับจากทีม",
          "value": "The Harmonizer"
        },
        {
          "text": "ติดต่อนักสำรวจท้องถิ่นที่รู้จักเส้นทางดีมาเป็นผู้นำทาง",
          "value": "The Networker"
        }
      ]
    },
    {
      "id": 4,
      "question": "ทีมกำลังท้อแท้หลังจากพลาดเป้าหมายหลายครั้ง คุณจะช่วยฟื้นฟูกำลังใจอย่างไร?",
      "answers": [
        {
          "text": "จัดกิจกรรมสนุกๆ เช่น การแข่งขันยิงธนูหรือเล่านิทานผจญภัยรอบกองไฟ เพื่อกระชับความสัมพันธ์ในทีม",
          "value": "The Maestro"
        },
        {
          "text": "ชวนทุกคนแบ่งปันความรู้สึกและประสบการณ์ พร้อมทั้งให้กำลังใจกันและกัน",
          "value": "The Harmonizer"
        },
        {
          "text": "เล่าเรื่องราวความสำเร็จของนักผจญภัยในตำนานที่เคยเผชิญอุปสรรคคล้ายกัน เพื่อสร้างแรงบันดาลใจ",
          "value": "The Networker"
        }
      ]
    }
  ],
  "Thought": [
    {
      "id": 1,
      "question": "ทีมต้องแก้ปริศนาโบราณเพื่อเปิดประตูลับ คุณจะช่วยยังไง?",
      "answers": [
        {
          "text": "ใช้จินตนาการและความคิดสร้างสรรค์เพื่อมองปริศนาในมุมที่แตกต่าง",
          "value": "The Imagineer"
        },
        {
          "text": "วิเคราะห์ปริศนาอย่างละเอียดและพิจารณาทุกความเป็นไปได้",
          "value": "The Oracle"
        },
        {
          "text": "นำความรู้เฉพาะทางเกี่ยวกับประวัติศาสตร์และโบราณคดีมาช่วยตีความ",
          "value": "The Sage"
        }
      ]
    },
    {
      "id": 2,
      "question": "ทีมกำลังวางแผนกลยุทธ์ในการเอาชนะมังกรที่เฝ้าสมบัติ คุณจะเสนออะไร?",
      "answers": [
        {
          "text": "คิดวิธีแปลกใหม่ในการเบี่ยงเบนความสนใจของมังกร",
          "value": "The Imagineer"
        },
        {
          "text": "วิเคราะห์จุดแข็งจุดอ่อนของมังกรเพื่อวางแผนโจมตี ",
          "value": "The Oracle"
        },
        {
          "text": "ใช้ความรู้เกี่ยวกับพฤติกรรมของมังกรเพื่อหาวิธีเข้าใกล้อย่างปลอดภัย",
          "value": "The Sage"
        }
      ]
    },
    {
      "id": 3,
      "question": "ทีมต้องข้ามหุบเหวลึกที่มีสะพานเชือกเก่าแก่ คุณจะจัดการอย่างไร",
      "answers": [
        {
          "text": "ประดิษฐ์วิธีการข้ามแบบใหม่โดยใช้อุปกรณ์ที่มีอยู่",
          "value": "The Imagineer"
        },
        {
          "text": "วิเคราะห์โครงสร้างสะพานและคำนวณความเสี่ยงในการข้าม",
          "value": "The Oracle"
        },
        {
          "text": "ใช้ความรู้เรื่องเทคนิคการผูกเงื่อนและการรับน้ำหนักของวัสดุเพื่อเสริมความแข็งแรงของสะพาน",
          "value": "The Sage"
        }
      ]
    },
    {
      "id": 4,
      "question": "ทีมเดินมาพักที่ใต้ต้นไม้ มองขึ้นไปเห็นเมฆ คุณจะ...",
      "answers": [
        {
          "text": "ชวนเพื่อนจินตนาการว่าเมฆที่เห็นคล้ายกับอะไรบ้าง",
          "value": "The Imagineer"
        },
        {
          "text": "ประเมินว่าเมฆก้อนที่เห็นจะทำให้เกิดฝน แล้วต้องหลบฝนหรือไม่",
          "value": "The Oracle"
        },
        {
          "text": "เล่าให้เพื่อนฟังว่าเมฆมีกี่ประเภท และนี่คือประเภทใด เกิดจากอะไร",
          "value": "The Sage"
        }
      ]
    }
  ]
}
